{
    "version": "0.40.2",
    "description": "SystemLink Integrator CLI",
    "homepage": "https://github.com/ni-kismet/systemlink-cli",
    "license": "MIT",
    "architecture": {
        "64bit": {
            "url": "https://github.com/ni-kismet/systemlink-cli/releases/download/v0.40.2/slcli.zip",
            "hash": "6CDC76C5199667F2FD7C18F3497062A798BE7199D49223BB9FEC7A53FD4DCBE3"
        }
    },
    "extract_dir": "slcli",
    "bin": "slcli.exe",
    "checkver": {
        "github": "https://github.com/ni-kismet/systemlink-cli"
    },
    "autoupdate": {
        "architecture": {
            "64bit": {
                "url": "https://github.com/ni-kismet/systemlink-cli/releases/download/v$version/slcli.zip"
            }
        }
    }
}
